hyperfastpy/__cli__.py
hyperfastpy/__init__.py
hyperfastpy/_version.py
hyperfastpy/conf/about/hyperfastpy.yaml
hyperfastpy/py.typed
hyperfast_python_template-0.16.3.dist-info/LICENSE
hyperfast_python_template-0.16.3.dist-info/METADATA
hyperfast_python_template-0.16.3.dist-info/WHEEL
hyperfast_python_template-0.16.3.dist-info/entry_points.txt
hyperfast_python_template-0.16.3.dist-info/RECORD
