Metadata-Version: 2.1
Name: hyperfast-python-template
Version: 0.16.3
Summary: Streamlining Python Project Development with a Comprehensive Toolset for Quality, Efficiency, and Maintainability
Home-page: https://hyperfast-python.entelecheia.ai
License: MIT
Author: Young Joon Lee
Author-email: entelecheia@hotmail.com
Requires-Python: >=3.9,<3.13
Classifier: License :: OSI Approved :: MIT License
Classifier: Programming Language :: Python :: 3
Classifier: Programming Language :: Python :: 3.9
Classifier: Programming Language :: Python :: 3.10
Classifier: Programming Language :: Python :: 3.11
Classifier: Programming Language :: Python :: 3.12
Requires-Dist: click (>=8.1.3,<9.0.0)
Project-URL: Repository, https://github.com/entelecheia/hyperfast-python-template
